chinus_tools/__init__.py
chinus_tools/inputs/__init__.py
chinus_tools/inputs/inputs.py
chinus_tools/jsons/__init__.py
chinus_tools/jsons/jsons.py
chinus_tools/prints/__init__.py
chinus_tools/prints/prints.py
chinus_tools/rand/__init__.py
chinus_tools/rand/gauss.py
chinus_tools-1.1.1.dist-info/METADATA
chinus_tools-1.1.1.dist-info/WHEEL
chinus_tools-1.1.1.dist-info/top_level.txt
chinus_tools-1.1.1.dist-info/RECORD
